{"Instance": "fastxgemm-n2r6s0t2_0_100", "Type": "mixed-integer", "Class": "general-bilevel", "Path": "https://cibolib.github.io/jsons/collection/mip-mip/general-bilevel/mixed-integer/MIPLIB2017", "ulNumVariables": 392, "ulNumIntVariables": 0, "ulNumBinVariables": 46, "llNumVariables": 392, "llNumIntVariables": 0, "llNumBinVariables": 2, "llNumVariablesWithLB": 392, "llNumVariablesWithUB": 392, "linkNumVariables": 392, "linkNumIntVariables": 0, "linkNumBinVariables": 46, "linkVariablesMinLB": -1, "linkVariablesMaxUB": 1, "ulNumConstraints": 0, "llNumConstraints": 5998}