{"Instance": "sing44_0_100", "Type": "mixed-integer", "Class": "general-bilevel", "Path": "https://cibolib.github.io/jsons/collection/mip-mip/general-bilevel/mixed-integer/MIPLIB2017", "ulNumVariables": 29854, "ulNumIntVariables": 0, "ulNumBinVariables": 13670, "llNumVariables": 29854, "llNumIntVariables": 0, "llNumBinVariables": 29854, "llNumVariablesWithLB": 29854, "llNumVariablesWithUB": 29854, "linkNumVariables": 29854, "linkNumIntVariables": 0, "linkNumBinVariables": 13670, "linkVariablesMinLB": 0, "linkVariablesMaxUB": 1e+100, "ulNumConstraints": 0, "llNumConstraints": 54745}