{
    "name": "K5010W18.KNP",
    "bilevel_type": "optimistic",
    "status": "optimal",
    "difficulty": "easy",
    "objective_value": 1580.0,
    "upper_level_decisions": {
        "x0": -0.0,
        "x1": 1.0,
        "x2": 1.0,
        "x3": -0.0,
        "x4": -0.0,
        "x5": 1.0,
        "x6": -0.0,
        "x7": 1.0,
        "x8": -0.0,
        "x9": 1.0
    },
    "lower_level_decisions": {
        "C0000000": 1.0,
        "C0000001": -0.0,
        "C0000002": -0.0,
        "C0000003": 0.0,
        "C0000004": 1.0,
        "C0000005": -0.0,
        "C0000006": 1.0,
        "C0000007": -0.0,
        "C0000008": 1.0,
        "C0000009": -0.0
    }
}