{
    "name": "normalClique50-90-9",
    "bilevel_type": "optimistic",
    "status": "open with feasible point",
    "difficulty": "hard",
    "objective_value": 11.0,
    "upper_level_decisions": {
        "w0,1": 0.0,
        "w0,2": 1.0,
        "w0,3": 0.0,
        "w0,4": 0.0,
        "w0,5": 0.0,
        "w0,7": 0.0,
        "w0,8": 0.0,
        "w0,9": 1.0,
        "w0,10": 0.0,
        "w0,11": 0.0,
        "w0,12": 1.0,
        "w0,13": 1.0,
        "w0,14": 1.0,
        "w0,15": 0.0,
        "w0,16": 1.0,
        "w0,19": 0.0,
        "w0,20": 1.0,
        "w0,21": 0.0,
        "w0,22": 0.0,
        "w0,23": 0.0,
        "w0,24": 0.0,
        "w0,25": 0.0,
        "w0,26": 0.0,
        "w0,27": 0.0,
        "w0,28": 0.0,
        "w0,29": 0.0,
        "w0,30": 0.0,
        "w0,31": 0.0,
        "w0,32": 1.0,
        "w0,33": 0.0,
        "w0,34": 1.0,
        "w0,35": 0.0,
        "w0,37": 1.0,
        "w0,39": 0.0,
        "w0,41": 1.0,
        "w0,42": 0.0,
        "w0,43": 0.0,
        "w0,44": 0.0,
        "w0,46": 1.0,
        "w0,47": 0.0,
        "w0,48": 0.0,
        "w1,2": 1.0,
        "w1,3": 0.0,
        "w1,4": 0.0,
        "w1,5": 1.0,
        "w1,7": 0.0,
        "w1,8": 1.0,
        "w1,9": 0.0,
        "w1,10": 0.0,
        "w1,11": 1.0,
        "w1,12": 0.0,
        "w1,13": 1.0,
        "w1,14": 1.0,
        "w1,15": 0.0,
        "w1,16": 0.0,
        "w1,18": 0.0,
        "w1,19": 0.0,
        "w1,20": 0.0,
        "w1,21": 1.0,
        "w1,22": 0.0,
        "w1,23": 0.0,
        "w1,24": 1.0,
        "w1,25": 0.0,
        "w1,26": 1.0,
        "w1,27": 0.0,
        "w1,28": 0.0,
        "w1,29": 0.0,
        "w1,30": 0.0,
        "w1,31": 0.0,
        "w1,32": 0.0,
        "w1,33": 0.0,
        "w1,34": 0.0,
        "w1,35": 0.0,
        "w1,36": 0.0,
        "w1,37": 0.0,
        "w1,38": 1.0,
        "w1,39": 0.0,
        "w1,41": 1.0,
        "w1,43": 1.0,
        "w1,44": 1.0,
        "w1,45": 0.0,
        "w1,46": 0.0,
        "w1,47": 0.0,
        "w1,48": 0.0,
        "w1,49": 0.0,
        "w2,3": 0.0,
        "w2,4": 1.0,
        "w2,5": 0.0,
        "w2,6": 1.0,
        "w2,7": 0.0,
        "w2,8": 0.0,
        "w2,9": 0.0,
        "w2,10": 1.0,
        "w2,11": 0.0,
        "w2,12": 0.0,
        "w2,13": 1.0,
        "w2,14": 0.0,
        "w2,17": 0.0,
        "w2,18": 0.0,
        "w2,19": 0.0,
        "w2,20": 0.0,
        "w2,21": 0.0,
        "w2,22": 0.0,
        "w2,23": 0.0,
        "w2,24": 0.0,
        "w2,25": 0.0,
        "w2,26": 0.0,
        "w2,27": 0.0,
        "w2,28": 0.0,
        "w2,29": 0.0,
        "w2,30": 1.0,
        "w2,31": 1.0,
        "w2,32": 1.0,
        "w2,33": 0.0,
        "w2,34": 1.0,
        "w2,35": 0.0,
        "w2,36": 1.0,
        "w2,38": 0.0,
        "w2,39": 0.0,
        "w2,40": 0.0,
        "w2,41": 0.0,
        "w2,42": 0.0,
        "w2,43": 0.0,
        "w2,44": 1.0,
        "w2,45": 0.0,
        "w2,46": 1.0,
        "w2,47": 1.0,
        "w2,48": 0.0,
        "w2,49": 0.0,
        "w3,4": 0.0,
        "w3,6": 1.0,
        "w3,7": 0.0,
        "w3,8": 0.0,
        "w3,9": 0.0,
        "w3,10": 0.0,
        "w3,13": 0.0,
        "w3,14": 0.0,
        "w3,15": 0.0,
        "w3,16": 0.0,
        "w3,17": 0.0,
        "w3,19": 0.0,
        "w3,20": 0.0,
        "w3,21": 0.0,
        "w3,22": 0.0,
        "w3,23": 0.0,
        "w3,24": 1.0,
        "w3,25": 0.0,
        "w3,26": 0.0,
        "w3,27": 0.0,
        "w3,28": 0.0,
        "w3,29": 0.0,
        "w3,31": 0.0,
        "w3,32": 0.0,
        "w3,33": 0.0,
        "w3,34": 0.0,
        "w3,35": 1.0,
        "w3,36": 0.0,
        "w3,37": 0.0,
        "w3,38": 0.0,
        "w3,39": 1.0,
        "w3,40": 0.0,
        "w3,41": 0.0,
        "w3,42": 1.0,
        "w3,43": 0.0,
        "w3,44": 1.0,
        "w3,45": 0.0,
        "w3,46": 1.0,
        "w3,47": 0.0,
        "w3,49": 0.0,
        "w4,5": 0.0,
        "w4,6": 1.0,
        "w4,7": 0.0,
        "w4,8": 1.0,
        "w4,9": 0.0,
        "w4,10": 0.0,
        "w4,11": 0.0,
        "w4,12": 0.0,
        "w4,13": 1.0,
        "w4,14": 0.0,
        "w4,15": 0.0,
        "w4,16": 1.0,
        "w4,17": 0.0,
        "w4,18": 0.0,
        "w4,20": 0.0,
        "w4,21": 0.0,
        "w4,22": 0.0,
        "w4,23": 0.0,
        "w4,24": 1.0,
        "w4,25": 0.0,
        "w4,26": 0.0,
        "w4,27": 0.0,
        "w4,28": 0.0,
        "w4,29": 0.0,
        "w4,30": 0.0,
        "w4,31": 0.0,
        "w4,32": 0.0,
        "w4,33": 0.0,
        "w4,34": 0.0,
        "w4,35": 1.0,
        "w4,36": 0.0,
        "w4,37": 0.0,
        "w4,38": 0.0,
        "w4,39": 0.0,
        "w4,40": 0.0,
        "w4,41": 0.0,
        "w4,43": 1.0,
        "w4,44": 0.0,
        "w4,45": 0.0,
        "w4,46": 0.0,
        "w4,48": 0.0,
        "w4,49": 1.0,
        "w5,6": 0.0,
        "w5,7": 0.0,
        "w5,8": 1.0,
        "w5,9": 0.0,
        "w5,10": 0.0,
        "w5,11": 1.0,
        "w5,12": 1.0,
        "w5,13": 1.0,
        "w5,14": 1.0,
        "w5,15": 0.0,
        "w5,16": 0.0,
        "w5,17": 1.0,
        "w5,18": 0.0,
        "w5,19": 1.0,
        "w5,21": 0.0,
        "w5,22": 0.0,
        "w5,23": 1.0,
        "w5,24": 1.0,
        "w5,25": 1.0,
        "w5,27": 1.0,
        "w5,29": 1.0,
        "w5,30": 1.0,
        "w5,31": 0.0,
        "w5,32": 1.0,
        "w5,33": 1.0,
        "w5,35": 1.0,
        "w5,36": 1.0,
        "w5,37": 1.0,
        "w5,38": 1.0,
        "w5,39": 1.0,
        "w5,40": 1.0,
        "w5,41": 1.0,
        "w5,42": 1.0,
        "w5,43": 1.0,
        "w5,44": 1.0,
        "w5,45": 1.0,
        "w5,47": 1.0,
        "w5,48": 0.0,
        "w6,7": 0.0,
        "w6,8": 1.0,
        "w6,9": 1.0,
        "w6,10": 1.0,
        "w6,11": 0.0,
        "w6,12": 0.0,
        "w6,13": 0.0,
        "w6,14": 0.0,
        "w6,15": 1.0,
        "w6,16": 1.0,
        "w6,17": 1.0,
        "w6,18": 0.0,
        "w6,19": 0.0,
        "w6,20": 0.0,
        "w6,21": 0.0,
        "w6,22": 1.0,
        "w6,23": 0.0,
        "w6,24": 0.0,
        "w6,25": 0.0,
        "w6,26": 0.0,
        "w6,27": 0.0,
        "w6,28": 1.0,
        "w6,29": 1.0,
        "w6,30": 0.0,
        "w6,31": 1.0,
        "w6,32": 0.0,
        "w6,33": 0.0,
        "w6,34": 0.0,
        "w6,36": 0.0,
        "w6,37": 1.0,
        "w6,38": 0.0,
        "w6,39": 0.0,
        "w6,40": 0.0,
        "w6,41": 0.0,
        "w6,43": 0.0,
        "w6,44": 0.0,
        "w6,45": 0.0,
        "w6,46": 0.0,
        "w6,47": 1.0,
        "w6,48": 0.0,
        "w6,49": 0.0,
        "w7,8": 0.0,
        "w7,9": 0.0,
        "w7,10": 0.0,
        "w7,11": 0.0,
        "w7,13": 1.0,
        "w7,14": 0.0,
        "w7,15": 0.0,
        "w7,16": 0.0,
        "w7,17": 0.0,
        "w7,18": 1.0,
        "w7,19": 0.0,
        "w7,20": 0.0,
        "w7,21": 0.0,
        "w7,22": 1.0,
        "w7,23": 0.0,
        "w7,24": 0.0,
        "w7,25": 0.0,
        "w7,26": 0.0,
        "w7,27": 0.0,
        "w7,29": 0.0,
        "w7,30": 0.0,
        "w7,31": 1.0,
        "w7,32": 1.0,
        "w7,33": 0.0,
        "w7,34": 1.0,
        "w7,35": 1.0,
        "w7,36": 0.0,
        "w7,37": 0.0,
        "w7,38": 0.0,
        "w7,40": 0.0,
        "w7,43": 1.0,
        "w7,44": 0.0,
        "w7,45": 0.0,
        "w7,46": 0.0,
        "w7,47": 0.0,
        "w7,48": 1.0,
        "w8,9": 0.0,
        "w8,10": 0.0,
        "w8,11": 0.0,
        "w8,12": 0.0,
        "w8,13": 0.0,
        "w8,14": 0.0,
        "w8,15": 1.0,
        "w8,16": 1.0,
        "w8,17": 0.0,
        "w8,18": 1.0,
        "w8,19": 1.0,
        "w8,20": 1.0,
        "w8,22": 0.0,
        "w8,23": 0.0,
        "w8,24": 0.0,
        "w8,25": 0.0,
        "w8,26": 0.0,
        "w8,27": 0.0,
        "w8,28": 0.0,
        "w8,29": 0.0,
        "w8,30": 0.0,
        "w8,31": 0.0,
        "w8,33": 0.0,
        "w8,34": 0.0,
        "w8,35": 0.0,
        "w8,36": 0.0,
        "w8,37": 1.0,
        "w8,38": 0.0,
        "w8,39": 0.0,
        "w8,41": 0.0,
        "w8,42": 0.0,
        "w8,43": 0.0,
        "w8,44": 0.0,
        "w8,45": 0.0,
        "w8,46": 0.0,
        "w8,47": 1.0,
        "w8,48": 0.0,
        "w8,49": 0.0,
        "w9,11": 0.0,
        "w9,12": 0.0,
        "w9,13": 0.0,
        "w9,14": 1.0,
        "w9,15": 0.0,
        "w9,16": 0.0,
        "w9,17": 0.0,
        "w9,18": 0.0,
        "w9,19": 0.0,
        "w9,21": 0.0,
        "w9,22": 1.0,
        "w9,23": 0.0,
        "w9,24": 0.0,
        "w9,25": 0.0,
        "w9,26": 1.0,
        "w9,27": 0.0,
        "w9,28": 1.0,
        "w9,29": 0.0,
        "w9,30": 0.0,
        "w9,31": 1.0,
        "w9,32": 0.0,
        "w9,33": 0.0,
        "w9,34": 0.0,
        "w9,35": 0.0,
        "w9,36": 0.0,
        "w9,37": 0.0,
        "w9,38": 1.0,
        "w9,39": 1.0,
        "w9,40": 0.0,
        "w9,41": 0.0,
        "w9,42": 0.0,
        "w9,43": 1.0,
        "w9,44": 0.0,
        "w9,45": 0.0,
        "w9,46": 1.0,
        "w9,47": 0.0,
        "w9,48": 0.0,
        "w9,49": 0.0,
        "w10,11": 0.0,
        "w10,12": 0.0,
        "w10,13": 1.0,
        "w10,14": 1.0,
        "w10,15": 1.0,
        "w10,16": 1.0,
        "w10,18": 0.0,
        "w10,19": 1.0,
        "w10,21": 0.0,
        "w10,23": 0.0,
        "w10,24": 0.0,
        "w10,25": 0.0,
        "w10,26": 0.0,
        "w10,27": 0.0,
        "w10,28": 1.0,
        "w10,29": 0.0,
        "w10,30": 0.0,
        "w10,31": 1.0,
        "w10,33": 0.0,
        "w10,34": 0.0,
        "w10,35": 0.0,
        "w10,36": 1.0,
        "w10,37": 1.0,
        "w10,38": 1.0,
        "w10,40": 0.0,
        "w10,41": 0.0,
        "w10,42": 0.0,
        "w10,43": 0.0,
        "w10,44": 1.0,
        "w10,45": 0.0,
        "w10,47": 1.0,
        "w10,48": 0.0,
        "w10,49": 0.0,
        "w11,12": 1.0,
        "w11,13": 1.0,
        "w11,14": 0.0,
        "w11,15": 0.0,
        "w11,16": 0.0,
        "w11,17": 0.0,
        "w11,18": 0.0,
        "w11,19": 0.0,
        "w11,20": 0.0,
        "w11,21": 0.0,
        "w11,22": 0.0,
        "w11,23": 0.0,
        "w11,25": 1.0,
        "w11,26": 0.0,
        "w11,27": 0.0,
        "w11,28": 0.0,
        "w11,29": 0.0,
        "w11,30": 0.0,
        "w11,31": 0.0,
        "w11,32": 0.0,
        "w11,33": 0.0,
        "w11,34": 0.0,
        "w11,35": 0.0,
        "w11,38": 0.0,
        "w11,39": 0.0,
        "w11,40": 0.0,
        "w11,41": 0.0,
        "w11,43": 0.0,
        "w11,44": 0.0,
        "w11,45": 0.0,
        "w11,46": 0.0,
        "w11,47": 0.0,
        "w11,48": 0.0,
        "w11,49": 0.0,
        "w12,13": 0.0,
        "w12,14": 0.0,
        "w12,15": 0.0,
        "w12,16": 0.0,
        "w12,17": 0.0,
        "w12,18": 0.0,
        "w12,19": 0.0,
        "w12,21": 1.0,
        "w12,22": 0.0,
        "w12,24": 0.0,
        "w12,25": 0.0,
        "w12,26": 0.0,
        "w12,28": 0.0,
        "w12,29": 0.0,
        "w12,30": 0.0,
        "w12,31": 0.0,
        "w12,32": 1.0,
        "w12,33": 0.0,
        "w12,34": 0.0,
        "w12,35": 0.0,
        "w12,36": 0.0,
        "w12,37": 0.0,
        "w12,38": 0.0,
        "w12,39": 0.0,
        "w12,40": 0.0,
        "w12,41": 1.0,
        "w12,42": 0.0,
        "w12,43": 0.0,
        "w12,45": 1.0,
        "w12,47": 1.0,
        "w12,48": 0.0,
        "w13,14": 0.0,
        "w13,15": 1.0,
        "w13,16": 0.0,
        "w13,17": 0.0,
        "w13,18": 0.0,
        "w13,20": 0.0,
        "w13,21": 0.0,
        "w13,22": 1.0,
        "w13,23": 0.0,
        "w13,25": 0.0,
        "w13,26": 0.0,
        "w13,27": 0.0,
        "w13,28": 0.0,
        "w13,29": 1.0,
        "w13,30": 1.0,
        "w13,31": 0.0,
        "w13,32": 0.0,
        "w13,33": 0.0,
        "w13,34": 1.0,
        "w13,35": 0.0,
        "w13,36": 0.0,
        "w13,37": 0.0,
        "w13,38": 0.0,
        "w13,40": 0.0,
        "w13,41": 0.0,
        "w13,42": 1.0,
        "w13,43": 1.0,
        "w13,44": 0.0,
        "w13,45": 1.0,
        "w13,47": 1.0,
        "w13,48": 0.0,
        "w13,49": 0.0,
        "w14,15": 0.0,
        "w14,16": 1.0,
        "w14,18": 0.0,
        "w14,19": 1.0,
        "w14,20": 1.0,
        "w14,21": 0.0,
        "w14,22": 1.0,
        "w14,23": 0.0,
        "w14,24": 0.0,
        "w14,25": 1.0,
        "w14,26": 0.0,
        "w14,27": 0.0,
        "w14,28": 0.0,
        "w14,29": 0.0,
        "w14,30": 0.0,
        "w14,32": 0.0,
        "w14,33": 1.0,
        "w14,35": 1.0,
        "w14,37": 0.0,
        "w14,38": 1.0,
        "w14,39": 1.0,
        "w14,40": 1.0,
        "w14,41": 0.0,
        "w14,42": 0.0,
        "w14,43": 0.0,
        "w14,44": 0.0,
        "w14,45": 0.0,
        "w14,46": 0.0,
        "w14,47": 0.0,
        "w15,16": 1.0,
        "w15,17": 0.0,
        "w15,18": 0.0,
        "w15,19": 0.0,
        "w15,20": 0.0,
        "w15,22": 0.0,
        "w15,23": 0.0,
        "w15,24": 0.0,
        "w15,25": 0.0,
        "w15,26": 0.0,
        "w15,27": 1.0,
        "w15,28": 0.0,
        "w15,29": 0.0,
        "w15,30": 0.0,
        "w15,31": 1.0,
        "w15,32": 0.0,
        "w15,33": 0.0,
        "w15,34": 1.0,
        "w15,35": 1.0,
        "w15,36": 0.0,
        "w15,37": 0.0,
        "w15,39": 0.0,
        "w15,40": 0.0,
        "w15,41": 1.0,
        "w15,42": 0.0,
        "w15,43": 0.0,
        "w15,44": 0.0,
        "w15,45": 0.0,
        "w15,46": 0.0,
        "w15,47": 0.0,
        "w15,49": 1.0,
        "w16,17": 0.0,
        "w16,18": 0.0,
        "w16,19": 0.0,
        "w16,20": 0.0,
        "w16,21": 0.0,
        "w16,22": 0.0,
        "w16,23": 1.0,
        "w16,24": 0.0,
        "w16,25": 0.0,
        "w16,26": 0.0,
        "w16,27": 0.0,
        "w16,28": 1.0,
        "w16,29": 0.0,
        "w16,30": 1.0,
        "w16,31": 0.0,
        "w16,32": 0.0,
        "w16,33": 0.0,
        "w16,34": 0.0,
        "w16,35": 1.0,
        "w16,36": 0.0,
        "w16,37": 0.0,
        "w16,38": 0.0,
        "w16,39": 0.0,
        "w16,40": 0.0,
        "w16,41": 0.0,
        "w16,42": 0.0,
        "w16,43": 0.0,
        "w16,44": 0.0,
        "w16,45": 0.0,
        "w16,46": 0.0,
        "w16,48": 0.0,
        "w17,19": 0.0,
        "w17,20": 0.0,
        "w17,21": 0.0,
        "w17,23": 0.0,
        "w17,24": 0.0,
        "w17,25": 1.0,
        "w17,26": 1.0,
        "w17,27": 0.0,
        "w17,28": 0.0,
        "w17,29": 0.0,
        "w17,30": 0.0,
        "w17,31": 0.0,
        "w17,32": 0.0,
        "w17,33": 0.0,
        "w17,34": 1.0,
        "w17,35": 0.0,
        "w17,36": 0.0,
        "w17,37": 0.0,
        "w17,38": 0.0,
        "w17,39": 0.0,
        "w17,40": 0.0,
        "w17,41": 0.0,
        "w17,42": 0.0,
        "w17,43": 1.0,
        "w17,44": 0.0,
        "w17,45": 0.0,
        "w17,46": 0.0,
        "w17,47": 0.0,
        "w17,49": 0.0,
        "w18,19": 0.0,
        "w18,20": 0.0,
        "w18,22": 0.0,
        "w18,23": 0.0,
        "w18,24": 1.0,
        "w18,25": 0.0,
        "w18,26": 0.0,
        "w18,27": 0.0,
        "w18,28": 1.0,
        "w18,29": 0.0,
        "w18,31": 1.0,
        "w18,32": 1.0,
        "w18,33": 1.0,
        "w18,34": 0.0,
        "w18,35": 0.0,
        "w18,36": 0.0,
        "w18,37": 0.0,
        "w18,38": 0.0,
        "w18,39": 1.0,
        "w18,41": 0.0,
        "w18,42": 1.0,
        "w18,43": 0.0,
        "w18,44": 0.0,
        "w18,45": 0.0,
        "w18,46": 1.0,
        "w18,47": 0.0,
        "w18,48": 0.0,
        "w18,49": 0.0,
        "w19,20": 0.0,
        "w19,21": 0.0,
        "w19,22": 0.0,
        "w19,23": 0.0,
        "w19,24": 0.0,
        "w19,25": 0.0,
        "w19,26": 0.0,
        "w19,27": 1.0,
        "w19,28": 0.0,
        "w19,29": 1.0,
        "w19,30": 0.0,
        "w19,31": 0.0,
        "w19,32": 0.0,
        "w19,33": 1.0,
        "w19,34": 0.0,
        "w19,35": 0.0,
        "w19,36": 0.0,
        "w19,37": 1.0,
        "w19,38": 0.0,
        "w19,40": 0.0,
        "w19,42": 0.0,
        "w19,43": 1.0,
        "w19,44": 0.0,
        "w19,45": 0.0,
        "w19,46": 0.0,
        "w19,47": 0.0,
        "w19,48": 0.0,
        "w20,21": 0.0,
        "w20,22": 0.0,
        "w20,23": 0.0,
        "w20,24": 0.0,
        "w20,25": 0.0,
        "w20,26": 0.0,
        "w20,27": 0.0,
        "w20,28": 0.0,
        "w20,30": 0.0,
        "w20,31": 0.0,
        "w20,32": 0.0,
        "w20,33": 0.0,
        "w20,34": 0.0,
        "w20,35": 0.0,
        "w20,36": 0.0,
        "w20,37": 0.0,
        "w20,38": 0.0,
        "w20,39": 0.0,
        "w20,40": 0.0,
        "w20,41": 0.0,
        "w20,42": 0.0,
        "w20,43": 1.0,
        "w20,44": 1.0,
        "w20,47": 0.0,
        "w20,48": 0.0,
        "w20,49": 0.0,
        "w21,23": 0.0,
        "w21,24": 1.0,
        "w21,25": 1.0,
        "w21,26": 1.0,
        "w21,27": 1.0,
        "w21,28": 0.0,
        "w21,29": 0.0,
        "w21,31": 1.0,
        "w21,32": 0.0,
        "w21,33": 1.0,
        "w21,34": 0.0,
        "w21,35": 0.0,
        "w21,36": 1.0,
        "w21,37": 0.0,
        "w21,38": 0.0,
        "w21,39": 0.0,
        "w21,40": 0.0,
        "w21,41": 0.0,
        "w21,42": 0.0,
        "w21,43": 0.0,
        "w21,45": 0.0,
        "w21,46": 0.0,
        "w21,47": 0.0,
        "w21,49": 0.0,
        "w22,23": 0.0,
        "w22,24": 0.0,
        "w22,25": 0.0,
        "w22,26": 0.0,
        "w22,27": 0.0,
        "w22,28": 0.0,
        "w22,29": 0.0,
        "w22,30": 0.0,
        "w22,31": 1.0,
        "w22,32": 0.0,
        "w22,33": 1.0,
        "w22,34": 1.0,
        "w22,35": 1.0,
        "w22,36": 0.0,
        "w22,37": 0.0,
        "w22,38": 1.0,
        "w22,39": 0.0,
        "w22,40": 1.0,
        "w22,41": 0.0,
        "w22,43": 1.0,
        "w22,44": 0.0,
        "w22,45": 0.0,
        "w22,46": 1.0,
        "w22,47": 0.0,
        "w22,49": 1.0,
        "w23,24": 0.0,
        "w23,25": 0.0,
        "w23,26": 1.0,
        "w23,27": 0.0,
        "w23,28": 0.0,
        "w23,29": 0.0,
        "w23,30": 1.0,
        "w23,31": 0.0,
        "w23,32": 0.0,
        "w23,33": 0.0,
        "w23,34": 0.0,
        "w23,35": 0.0,
        "w23,37": 0.0,
        "w23,38": 0.0,
        "w23,39": 0.0,
        "w23,40": 0.0,
        "w23,41": 0.0,
        "w23,42": 0.0,
        "w23,43": 0.0,
        "w23,44": 0.0,
        "w23,45": 0.0,
        "w23,46": 0.0,
        "w23,47": 0.0,
        "w23,48": 0.0,
        "w23,49": 0.0,
        "w24,25": 0.0,
        "w24,26": 0.0,
        "w24,27": 0.0,
        "w24,28": 0.0,
        "w24,29": 0.0,
        "w24,30": 0.0,
        "w24,31": 0.0,
        "w24,32": 0.0,
        "w24,33": 1.0,
        "w24,34": 0.0,
        "w24,35": 0.0,
        "w24,36": 0.0,
        "w24,37": 0.0,
        "w24,38": 0.0,
        "w24,39": 0.0,
        "w24,40": 0.0,
        "w24,41": 0.0,
        "w24,42": 0.0,
        "w24,43": 0.0,
        "w24,44": 0.0,
        "w24,45": 0.0,
        "w24,46": 0.0,
        "w24,47": 0.0,
        "w24,48": 0.0,
        "w24,49": 0.0,
        "w25,26": 1.0,
        "w25,27": 0.0,
        "w25,28": 0.0,
        "w25,29": 0.0,
        "w25,32": 0.0,
        "w25,34": 0.0,
        "w25,35": 0.0,
        "w25,36": 0.0,
        "w25,37": 0.0,
        "w25,38": 0.0,
        "w25,39": 0.0,
        "w25,40": 0.0,
        "w25,41": 1.0,
        "w25,42": 1.0,
        "w25,43": 0.0,
        "w25,44": 0.0,
        "w25,45": 0.0,
        "w25,46": 0.0,
        "w25,47": 1.0,
        "w25,48": 0.0,
        "w25,49": 0.0,
        "w26,27": 0.0,
        "w26,28": 1.0,
        "w26,29": 0.0,
        "w26,30": 0.0,
        "w26,31": 0.0,
        "w26,32": 0.0,
        "w26,33": 0.0,
        "w26,34": 0.0,
        "w26,37": 1.0,
        "w26,38": 0.0,
        "w26,39": 1.0,
        "w26,40": 0.0,
        "w26,41": 0.0,
        "w26,43": 0.0,
        "w26,44": 0.0,
        "w26,46": 1.0,
        "w26,47": 0.0,
        "w26,48": 0.0,
        "w26,49": 1.0,
        "w27,28": 0.0,
        "w27,29": 1.0,
        "w27,30": 0.0,
        "w27,31": 0.0,
        "w27,32": 1.0,
        "w27,33": 0.0,
        "w27,34": 0.0,
        "w27,35": 0.0,
        "w27,36": 1.0,
        "w27,37": 1.0,
        "w27,38": 0.0,
        "w27,39": 0.0,
        "w27,40": 0.0,
        "w27,42": 0.0,
        "w27,43": 1.0,
        "w27,44": 1.0,
        "w27,45": 0.0,
        "w27,47": 0.0,
        "w27,48": 0.0,
        "w27,49": 0.0,
        "w28,29": 1.0,
        "w28,30": 0.0,
        "w28,31": 0.0,
        "w28,32": 1.0,
        "w28,33": 0.0,
        "w28,34": 0.0,
        "w28,35": 1.0,
        "w28,36": 0.0,
        "w28,37": 1.0,
        "w28,38": 0.0,
        "w28,39": 0.0,
        "w28,40": 0.0,
        "w28,41": 1.0,
        "w28,42": 0.0,
        "w28,43": 0.0,
        "w28,44": 0.0,
        "w28,45": 0.0,
        "w28,46": 0.0,
        "w28,47": 0.0,
        "w28,48": 0.0,
        "w28,49": 0.0,
        "w29,30": 0.0,
        "w29,31": 0.0,
        "w29,32": 0.0,
        "w29,33": 0.0,
        "w29,34": 0.0,
        "w29,36": 0.0,
        "w29,37": 1.0,
        "w29,38": 0.0,
        "w29,39": 0.0,
        "w29,40": 0.0,
        "w29,42": 0.0,
        "w29,43": 0.0,
        "w29,44": 0.0,
        "w29,45": 0.0,
        "w29,46": 0.0,
        "w29,48": 1.0,
        "w29,49": 0.0,
        "w30,32": 0.0,
        "w30,33": 0.0,
        "w30,34": 1.0,
        "w30,35": 1.0,
        "w30,36": 0.0,
        "w30,37": 0.0,
        "w30,38": 0.0,
        "w30,40": 0.0,
        "w30,41": 0.0,
        "w30,42": 0.0,
        "w30,43": 0.0,
        "w30,44": 0.0,
        "w30,46": 0.0,
        "w30,47": 0.0,
        "w30,48": 0.0,
        "w30,49": 1.0,
        "w31,32": 0.0,
        "w31,33": 0.0,
        "w31,34": 1.0,
        "w31,35": 0.0,
        "w31,36": 0.0,
        "w31,37": 0.0,
        "w31,38": 0.0,
        "w31,39": 1.0,
        "w31,40": 0.0,
        "w31,41": 0.0,
        "w31,42": 0.0,
        "w31,43": 1.0,
        "w31,44": 1.0,
        "w31,45": 0.0,
        "w31,46": 0.0,
        "w31,47": 0.0,
        "w31,48": 1.0,
        "w31,49": 0.0,
        "w32,34": 0.0,
        "w32,35": 0.0,
        "w32,36": 0.0,
        "w32,37": 0.0,
        "w32,38": 0.0,
        "w32,39": 1.0,
        "w32,40": 0.0,
        "w32,41": 0.0,
        "w32,42": 0.0,
        "w32,43": 0.0,
        "w32,44": 0.0,
        "w32,45": 1.0,
        "w32,46": 0.0,
        "w32,47": 0.0,
        "w32,48": 1.0,
        "w32,49": 0.0,
        "w33,34": 0.0,
        "w33,35": 0.0,
        "w33,36": 0.0,
        "w33,37": 0.0,
        "w33,38": 0.0,
        "w33,39": 0.0,
        "w33,40": 0.0,
        "w33,43": 0.0,
        "w33,44": 1.0,
        "w33,45": 1.0,
        "w33,46": 1.0,
        "w33,48": 1.0,
        "w33,49": 0.0,
        "w34,35": 0.0,
        "w34,36": 0.0,
        "w34,37": 0.0,
        "w34,38": 0.0,
        "w34,39": 0.0,
        "w34,40": 1.0,
        "w34,41": 0.0,
        "w34,42": 0.0,
        "w34,43": 1.0,
        "w34,44": 0.0,
        "w34,45": 1.0,
        "w34,46": 0.0,
        "w34,47": 0.0,
        "w34,48": 0.0,
        "w34,49": 0.0,
        "w35,36": 0.0,
        "w35,38": 0.0,
        "w35,41": 0.0,
        "w35,42": 0.0,
        "w35,43": 0.0,
        "w35,44": 1.0,
        "w35,45": 0.0,
        "w35,46": 0.0,
        "w35,47": 1.0,
        "w35,48": 0.0,
        "w35,49": 0.0,
        "w36,37": 0.0,
        "w36,38": 0.0,
        "w36,39": 1.0,
        "w36,40": 0.0,
        "w36,41": 0.0,
        "w36,43": 0.0,
        "w36,44": 0.0,
        "w36,45": 0.0,
        "w36,46": 1.0,
        "w36,47": 0.0,
        "w36,48": 1.0,
        "w36,49": 1.0,
        "w37,38": 0.0,
        "w37,39": 0.0,
        "w37,40": 0.0,
        "w37,41": 1.0,
        "w37,42": 1.0,
        "w37,43": 0.0,
        "w37,44": 1.0,
        "w37,45": 1.0,
        "w37,47": 0.0,
        "w37,48": 0.0,
        "w37,49": 0.0,
        "w38,39": 0.0,
        "w38,41": 1.0,
        "w38,42": 0.0,
        "w38,43": 0.0,
        "w38,44": 0.0,
        "w38,45": 0.0,
        "w38,46": 0.0,
        "w38,47": 0.0,
        "w38,48": 0.0,
        "w39,40": 0.0,
        "w39,41": 1.0,
        "w39,42": 0.0,
        "w39,43": 0.0,
        "w39,44": 1.0,
        "w39,45": 1.0,
        "w39,46": 0.0,
        "w39,47": 0.0,
        "w39,48": 0.0,
        "w39,49": 0.0,
        "w40,41": 0.0,
        "w40,42": 0.0,
        "w40,43": 1.0,
        "w40,44": 0.0,
        "w40,45": 1.0,
        "w40,46": 0.0,
        "w40,47": 0.0,
        "w40,48": 0.0,
        "w41,42": 0.0,
        "w41,43": 0.0,
        "w41,44": 0.0,
        "w41,45": 1.0,
        "w41,46": 0.0,
        "w41,48": 0.0,
        "w41,49": 0.0,
        "w42,43": 0.0,
        "w42,44": 0.0,
        "w42,45": 1.0,
        "w42,46": 0.0,
        "w42,47": 0.0,
        "w42,48": 0.0,
        "w42,49": 0.0,
        "w43,44": 0.0,
        "w43,45": 0.0,
        "w43,47": 0.0,
        "w43,48": 1.0,
        "w43,49": 1.0,
        "w44,45": 0.0,
        "w44,46": 1.0,
        "w44,47": 0.0,
        "w44,48": 0.0,
        "w44,49": 0.0,
        "w45,46": 1.0,
        "w45,47": 0.0,
        "w45,48": 0.0,
        "w45,49": 0.0,
        "w46,47": 1.0,
        "w46,48": 0.0,
        "w46,49": 0.0,
        "w47,48": 1.0,
        "w48,49": 0.0
    },
    "lower_level_decisions": {
        "y0,1": 1.0,
        "y0,2": 0.0,
        "y0,3": 1.0,
        "y0,4": 1.0,
        "y0,5": 1.0,
        "y0,7": 1.0,
        "y0,8": 1.0,
        "y0,9": 0.0,
        "y0,10": 1.0,
        "y0,11": 1.0,
        "y0,12": 0.0,
        "y0,13": 0.0,
        "y0,14": 0.0,
        "y0,15": 1.0,
        "y0,16": 0.0,
        "y0,19": 1.0,
        "y0,20": 0.0,
        "y0,21": 1.0,
        "y0,22": 1.0,
        "y0,23": 1.0,
        "y0,24": 1.0,
        "y0,25": 1.0,
        "y0,26": 1.0,
        "y0,27": 1.0,
        "y0,28": 1.0,
        "y0,29": 1.0,
        "y0,30": 1.0,
        "y0,31": 1.0,
        "y0,32": 0.0,
        "y0,33": 1.0,
        "y0,34": 0.0,
        "y0,35": 1.0,
        "y0,37": 0.0,
        "y0,39": 1.0,
        "y0,41": 0.0,
        "y0,42": 1.0,
        "y0,43": 1.0,
        "y0,44": 1.0,
        "y0,46": 0.0,
        "y0,47": 1.0,
        "y0,48": 1.0,
        "y1,2": 0.0,
        "y1,3": 1.0,
        "y1,4": 1.0,
        "y1,5": 0.0,
        "y1,7": 1.0,
        "y1,8": 0.0,
        "y1,9": 1.0,
        "y1,10": 1.0,
        "y1,11": 0.0,
        "y1,12": 1.0,
        "y1,13": 0.0,
        "y1,14": 0.0,
        "y1,15": 1.0,
        "y1,16": 1.0,
        "y1,18": 1.0,
        "y1,19": 1.0,
        "y1,20": 1.0,
        "y1,21": 0.0,
        "y1,22": 1.0,
        "y1,23": 1.0,
        "y1,24": 0.0,
        "y1,25": 1.0,
        "y1,26": 0.0,
        "y1,27": 1.0,
        "y1,28": 1.0,
        "y1,29": 1.0,
        "y1,30": 1.0,
        "y1,31": 1.0,
        "y1,32": 1.0,
        "y1,33": 1.0,
        "y1,34": 1.0,
        "y1,35": 1.0,
        "y1,36": 1.0,
        "y1,37": 1.0,
        "y1,38": 0.0,
        "y1,39": 1.0,
        "y1,41": 0.0,
        "y1,43": 0.0,
        "y1,44": 0.0,
        "y1,45": 1.0,
        "y1,46": 1.0,
        "y1,47": 1.0,
        "y1,48": 1.0,
        "y1,49": 1.0,
        "y2,3": 1.0,
        "y2,4": 0.0,
        "y2,5": 1.0,
        "y2,6": 0.0,
        "y2,7": 1.0,
        "y2,8": 1.0,
        "y2,9": 1.0,
        "y2,10": 0.0,
        "y2,11": 1.0,
        "y2,12": 1.0,
        "y2,13": 0.0,
        "y2,14": 1.0,
        "y2,17": 1.0,
        "y2,18": 1.0,
        "y2,19": 1.0,
        "y2,20": 1.0,
        "y2,21": 1.0,
        "y2,22": 1.0,
        "y2,23": 1.0,
        "y2,24": 1.0,
        "y2,25": 1.0,
        "y2,26": 1.0,
        "y2,27": 1.0,
        "y2,28": 1.0,
        "y2,29": 1.0,
        "y2,30": 0.0,
        "y2,31": 0.0,
        "y2,32": 0.0,
        "y2,33": 1.0,
        "y2,34": 0.0,
        "y2,35": 1.0,
        "y2,36": 0.0,
        "y2,38": 1.0,
        "y2,39": 1.0,
        "y2,40": 1.0,
        "y2,41": 1.0,
        "y2,42": 1.0,
        "y2,43": 1.0,
        "y2,44": 0.0,
        "y2,45": 1.0,
        "y2,46": 0.0,
        "y2,47": 0.0,
        "y2,48": 1.0,
        "y2,49": 1.0,
        "y3,4": 1.0,
        "y3,6": 0.0,
        "y3,7": 1.0,
        "y3,8": 1.0,
        "y3,9": 1.0,
        "y3,10": 1.0,
        "y3,13": 1.0,
        "y3,14": 1.0,
        "y3,15": 1.0,
        "y3,16": 1.0,
        "y3,17": 1.0,
        "y3,19": 1.0,
        "y3,20": 1.0,
        "y3,21": 1.0,
        "y3,22": 1.0,
        "y3,23": 1.0,
        "y3,24": 0.0,
        "y3,25": 1.0,
        "y3,26": 1.0,
        "y3,27": 1.0,
        "y3,28": 1.0,
        "y3,29": 1.0,
        "y3,31": 1.0,
        "y3,32": 1.0,
        "y3,33": 1.0,
        "y3,34": 1.0,
        "y3,35": 0.0,
        "y3,36": 1.0,
        "y3,37": 1.0,
        "y3,38": 1.0,
        "y3,39": 0.0,
        "y3,40": 1.0,
        "y3,41": 1.0,
        "y3,42": 0.0,
        "y3,43": 1.0,
        "y3,44": 0.0,
        "y3,45": 1.0,
        "y3,46": 0.0,
        "y3,47": 1.0,
        "y3,49": 1.0,
        "y4,5": 1.0,
        "y4,6": 0.0,
        "y4,7": 1.0,
        "y4,8": 0.0,
        "y4,9": 1.0,
        "y4,10": 1.0,
        "y4,11": 1.0,
        "y4,12": 1.0,
        "y4,13": 0.0,
        "y4,14": 1.0,
        "y4,15": 1.0,
        "y4,16": 0.0,
        "y4,17": 1.0,
        "y4,18": 1.0,
        "y4,20": 1.0,
        "y4,21": 1.0,
        "y4,22": 1.0,
        "y4,23": 1.0,
        "y4,24": 0.0,
        "y4,25": 1.0,
        "y4,26": 1.0,
        "y4,27": 1.0,
        "y4,28": 1.0,
        "y4,29": 1.0,
        "y4,30": 1.0,
        "y4,31": 1.0,
        "y4,32": 1.0,
        "y4,33": 1.0,
        "y4,34": 1.0,
        "y4,35": 0.0,
        "y4,36": 1.0,
        "y4,37": 1.0,
        "y4,38": 1.0,
        "y4,39": 1.0,
        "y4,40": 1.0,
        "y4,41": 1.0,
        "y4,43": 0.0,
        "y4,44": 1.0,
        "y4,45": 1.0,
        "y4,46": 1.0,
        "y4,48": 1.0,
        "y4,49": 0.0,
        "y5,6": 1.0,
        "y5,7": 1.0,
        "y5,8": 0.0,
        "y5,9": 1.0,
        "y5,10": 1.0,
        "y5,11": 0.0,
        "y5,12": 0.0,
        "y5,13": 0.0,
        "y5,14": 0.0,
        "y5,15": 1.0,
        "y5,16": 1.0,
        "y5,17": 0.0,
        "y5,18": 1.0,
        "y5,19": 0.0,
        "y5,21": 1.0,
        "y5,22": 1.0,
        "y5,23": 0.0,
        "y5,24": 0.0,
        "y5,25": 0.0,
        "y5,27": 0.0,
        "y5,29": 0.0,
        "y5,30": 0.0,
        "y5,31": 1.0,
        "y5,32": 0.0,
        "y5,33": 0.0,
        "y5,35": 0.0,
        "y5,36": 0.0,
        "y5,37": 0.0,
        "y5,38": 0.0,
        "y5,39": 0.0,
        "y5,40": 0.0,
        "y5,41": 0.0,
        "y5,42": 0.0,
        "y5,43": 0.0,
        "y5,44": 0.0,
        "y5,45": 0.0,
        "y5,47": 0.0,
        "y5,48": 1.0,
        "y6,7": 1.0,
        "y6,8": 0.0,
        "y6,9": 0.0,
        "y6,10": 0.0,
        "y6,11": 1.0,
        "y6,12": 1.0,
        "y6,13": 1.0,
        "y6,14": 1.0,
        "y6,15": 0.0,
        "y6,16": 0.0,
        "y6,17": 0.0,
        "y6,18": 1.0,
        "y6,19": 1.0,
        "y6,20": 1.0,
        "y6,21": 1.0,
        "y6,22": 0.0,
        "y6,23": 1.0,
        "y6,24": 1.0,
        "y6,25": 1.0,
        "y6,26": 1.0,
        "y6,27": 1.0,
        "y6,28": 0.0,
        "y6,29": 0.0,
        "y6,30": 1.0,
        "y6,31": 0.0,
        "y6,32": 1.0,
        "y6,33": 1.0,
        "y6,34": 1.0,
        "y6,36": 1.0,
        "y6,37": 0.0,
        "y6,38": 1.0,
        "y6,39": 1.0,
        "y6,40": 1.0,
        "y6,41": 1.0,
        "y6,43": 1.0,
        "y6,44": 1.0,
        "y6,45": 1.0,
        "y6,46": 1.0,
        "y6,47": 0.0,
        "y6,48": 1.0,
        "y6,49": 1.0,
        "y7,8": 1.0,
        "y7,9": 1.0,
        "y7,10": 1.0,
        "y7,11": 1.0,
        "y7,13": 0.0,
        "y7,14": 1.0,
        "y7,15": 1.0,
        "y7,16": 1.0,
        "y7,17": 1.0,
        "y7,18": 0.0,
        "y7,19": 1.0,
        "y7,20": 1.0,
        "y7,21": 1.0,
        "y7,22": 0.0,
        "y7,23": 1.0,
        "y7,24": 1.0,
        "y7,25": 1.0,
        "y7,26": 1.0,
        "y7,27": 1.0,
        "y7,29": 1.0,
        "y7,30": 1.0,
        "y7,31": 0.0,
        "y7,32": 0.0,
        "y7,33": 1.0,
        "y7,34": 0.0,
        "y7,35": 0.0,
        "y7,36": 1.0,
        "y7,37": 1.0,
        "y7,38": 1.0,
        "y7,40": 1.0,
        "y7,43": 0.0,
        "y7,44": 1.0,
        "y7,45": 1.0,
        "y7,46": 1.0,
        "y7,47": 1.0,
        "y7,48": 0.0,
        "y8,9": 1.0,
        "y8,10": 1.0,
        "y8,11": 1.0,
        "y8,12": 1.0,
        "y8,13": 1.0,
        "y8,14": 1.0,
        "y8,15": 0.0,
        "y8,16": 0.0,
        "y8,17": 1.0,
        "y8,18": 0.0,
        "y8,19": 0.0,
        "y8,20": 0.0,
        "y8,22": 1.0,
        "y8,23": 1.0,
        "y8,24": 1.0,
        "y8,25": 1.0,
        "y8,26": 1.0,
        "y8,27": 1.0,
        "y8,28": 1.0,
        "y8,29": 1.0,
        "y8,30": 1.0,
        "y8,31": 1.0,
        "y8,33": 1.0,
        "y8,34": 1.0,
        "y8,35": 1.0,
        "y8,36": 1.0,
        "y8,37": 0.0,
        "y8,38": 1.0,
        "y8,39": 1.0,
        "y8,41": 1.0,
        "y8,42": 1.0,
        "y8,43": 1.0,
        "y8,44": 1.0,
        "y8,45": 1.0,
        "y8,46": 1.0,
        "y8,47": 0.0,
        "y8,48": 1.0,
        "y8,49": 1.0,
        "y9,11": 1.0,
        "y9,12": 1.0,
        "y9,13": 1.0,
        "y9,14": 0.0,
        "y9,15": 1.0,
        "y9,16": 1.0,
        "y9,17": 1.0,
        "y9,18": 1.0,
        "y9,19": 1.0,
        "y9,21": 1.0,
        "y9,22": 0.0,
        "y9,23": 1.0,
        "y9,24": 1.0,
        "y9,25": 1.0,
        "y9,26": 0.0,
        "y9,27": 1.0,
        "y9,28": 0.0,
        "y9,29": 1.0,
        "y9,30": 1.0,
        "y9,31": 0.0,
        "y9,32": 1.0,
        "y9,33": 1.0,
        "y9,34": 1.0,
        "y9,35": 1.0,
        "y9,36": 1.0,
        "y9,37": 1.0,
        "y9,38": 0.0,
        "y9,39": 0.0,
        "y9,40": 1.0,
        "y9,41": 1.0,
        "y9,42": 1.0,
        "y9,43": 0.0,
        "y9,44": 1.0,
        "y9,45": 1.0,
        "y9,46": 0.0,
        "y9,47": 1.0,
        "y9,48": 1.0,
        "y9,49": 1.0,
        "y10,11": 1.0,
        "y10,12": 1.0,
        "y10,13": 0.0,
        "y10,14": 0.0,
        "y10,15": 0.0,
        "y10,16": 0.0,
        "y10,18": 1.0,
        "y10,19": 0.0,
        "y10,21": 1.0,
        "y10,23": 1.0,
        "y10,24": 1.0,
        "y10,25": 1.0,
        "y10,26": 1.0,
        "y10,27": 1.0,
        "y10,28": 0.0,
        "y10,29": 1.0,
        "y10,30": 1.0,
        "y10,31": 0.0,
        "y10,33": 1.0,
        "y10,34": 1.0,
        "y10,35": 1.0,
        "y10,36": 0.0,
        "y10,37": 0.0,
        "y10,38": 0.0,
        "y10,40": 1.0,
        "y10,41": 1.0,
        "y10,42": 1.0,
        "y10,43": 1.0,
        "y10,44": 0.0,
        "y10,45": 1.0,
        "y10,47": 0.0,
        "y10,48": 1.0,
        "y10,49": 1.0,
        "y11,12": 0.0,
        "y11,13": 0.0,
        "y11,14": 1.0,
        "y11,15": 1.0,
        "y11,16": 1.0,
        "y11,17": 1.0,
        "y11,18": 1.0,
        "y11,19": 1.0,
        "y11,20": 1.0,
        "y11,21": 1.0,
        "y11,22": 1.0,
        "y11,23": 1.0,
        "y11,25": 0.0,
        "y11,26": 1.0,
        "y11,27": 1.0,
        "y11,28": 1.0,
        "y11,29": 1.0,
        "y11,30": 1.0,
        "y11,31": 1.0,
        "y11,32": 1.0,
        "y11,33": 1.0,
        "y11,34": 1.0,
        "y11,35": 1.0,
        "y11,38": 1.0,
        "y11,39": 1.0,
        "y11,40": 1.0,
        "y11,41": 1.0,
        "y11,43": 1.0,
        "y11,44": 1.0,
        "y11,45": 1.0,
        "y11,46": 1.0,
        "y11,47": 1.0,
        "y11,48": 1.0,
        "y11,49": 1.0,
        "y12,13": 1.0,
        "y12,14": 1.0,
        "y12,15": 1.0,
        "y12,16": 1.0,
        "y12,17": 1.0,
        "y12,18": 1.0,
        "y12,19": 1.0,
        "y12,21": 0.0,
        "y12,22": 1.0,
        "y12,24": 1.0,
        "y12,25": 1.0,
        "y12,26": 1.0,
        "y12,28": 1.0,
        "y12,29": 1.0,
        "y12,30": 1.0,
        "y12,31": 1.0,
        "y12,32": 0.0,
        "y12,33": 1.0,
        "y12,34": 1.0,
        "y12,35": 1.0,
        "y12,36": 1.0,
        "y12,37": 1.0,
        "y12,38": 1.0,
        "y12,39": 1.0,
        "y12,40": 1.0,
        "y12,41": 0.0,
        "y12,42": 1.0,
        "y12,43": 1.0,
        "y12,45": 0.0,
        "y12,47": 0.0,
        "y12,48": 1.0,
        "y13,14": 1.0,
        "y13,15": 0.0,
        "y13,16": 1.0,
        "y13,17": 1.0,
        "y13,18": 1.0,
        "y13,20": 1.0,
        "y13,21": 1.0,
        "y13,22": 0.0,
        "y13,23": 1.0,
        "y13,25": 1.0,
        "y13,26": 1.0,
        "y13,27": 1.0,
        "y13,28": 1.0,
        "y13,29": 0.0,
        "y13,30": 0.0,
        "y13,31": 1.0,
        "y13,32": 1.0,
        "y13,33": 1.0,
        "y13,34": 0.0,
        "y13,35": 1.0,
        "y13,36": 1.0,
        "y13,37": 1.0,
        "y13,38": 1.0,
        "y13,40": 1.0,
        "y13,41": 1.0,
        "y13,42": 0.0,
        "y13,43": 0.0,
        "y13,44": 1.0,
        "y13,45": 0.0,
        "y13,47": 0.0,
        "y13,48": 1.0,
        "y13,49": 1.0,
        "y14,15": 1.0,
        "y14,16": 0.0,
        "y14,18": 1.0,
        "y14,19": 0.0,
        "y14,20": 0.0,
        "y14,21": 1.0,
        "y14,22": 0.0,
        "y14,23": 1.0,
        "y14,24": 1.0,
        "y14,25": 0.0,
        "y14,26": 1.0,
        "y14,27": 1.0,
        "y14,28": 1.0,
        "y14,29": 1.0,
        "y14,30": 1.0,
        "y14,32": 1.0,
        "y14,33": 0.0,
        "y14,35": 0.0,
        "y14,37": 1.0,
        "y14,38": 0.0,
        "y14,39": 0.0,
        "y14,40": 0.0,
        "y14,41": 1.0,
        "y14,42": 1.0,
        "y14,43": 1.0,
        "y14,44": 1.0,
        "y14,45": 1.0,
        "y14,46": 1.0,
        "y14,47": 1.0,
        "y15,16": 0.0,
        "y15,17": 1.0,
        "y15,18": 1.0,
        "y15,19": 1.0,
        "y15,20": 1.0,
        "y15,22": 1.0,
        "y15,23": 1.0,
        "y15,24": 1.0,
        "y15,25": 1.0,
        "y15,26": 1.0,
        "y15,27": 0.0,
        "y15,28": 1.0,
        "y15,29": 1.0,
        "y15,30": 1.0,
        "y15,31": 0.0,
        "y15,32": 1.0,
        "y15,33": 1.0,
        "y15,34": 0.0,
        "y15,35": 0.0,
        "y15,36": 1.0,
        "y15,37": 1.0,
        "y15,39": 1.0,
        "y15,40": 1.0,
        "y15,41": 0.0,
        "y15,42": 1.0,
        "y15,43": 1.0,
        "y15,44": 1.0,
        "y15,45": 1.0,
        "y15,46": 1.0,
        "y15,47": 1.0,
        "y15,49": 0.0,
        "y16,17": 1.0,
        "y16,18": 1.0,
        "y16,19": 1.0,
        "y16,20": 1.0,
        "y16,21": 1.0,
        "y16,22": 1.0,
        "y16,23": 0.0,
        "y16,24": 1.0,
        "y16,25": 1.0,
        "y16,26": 1.0,
        "y16,27": 1.0,
        "y16,28": 0.0,
        "y16,29": 1.0,
        "y16,30": 0.0,
        "y16,31": 1.0,
        "y16,32": 1.0,
        "y16,33": 1.0,
        "y16,34": 1.0,
        "y16,35": 0.0,
        "y16,36": 1.0,
        "y16,37": 1.0,
        "y16,38": 1.0,
        "y16,39": 1.0,
        "y16,40": 1.0,
        "y16,41": 1.0,
        "y16,42": 1.0,
        "y16,43": 1.0,
        "y16,44": 1.0,
        "y16,45": 1.0,
        "y16,46": 1.0,
        "y16,48": 1.0,
        "y17,19": 1.0,
        "y17,20": 1.0,
        "y17,21": 1.0,
        "y17,23": 1.0,
        "y17,24": 1.0,
        "y17,25": 0.0,
        "y17,26": 0.0,
        "y17,27": 1.0,
        "y17,28": 1.0,
        "y17,29": 1.0,
        "y17,30": 1.0,
        "y17,31": 1.0,
        "y17,32": 1.0,
        "y17,33": 1.0,
        "y17,34": 0.0,
        "y17,35": 1.0,
        "y17,36": 1.0,
        "y17,37": 1.0,
        "y17,38": 1.0,
        "y17,39": 1.0,
        "y17,40": 1.0,
        "y17,41": 1.0,
        "y17,42": 1.0,
        "y17,43": 0.0,
        "y17,44": 1.0,
        "y17,45": 1.0,
        "y17,46": 1.0,
        "y17,47": 1.0,
        "y17,49": 1.0,
        "y18,19": 1.0,
        "y18,20": 1.0,
        "y18,22": 1.0,
        "y18,23": 1.0,
        "y18,24": 0.0,
        "y18,25": 1.0,
        "y18,26": 1.0,
        "y18,27": 1.0,
        "y18,28": 0.0,
        "y18,29": 1.0,
        "y18,31": 0.0,
        "y18,32": 0.0,
        "y18,33": 0.0,
        "y18,34": 1.0,
        "y18,35": 1.0,
        "y18,36": 1.0,
        "y18,37": 1.0,
        "y18,38": 1.0,
        "y18,39": 0.0,
        "y18,41": 1.0,
        "y18,42": 0.0,
        "y18,43": 1.0,
        "y18,44": 1.0,
        "y18,45": 1.0,
        "y18,46": 0.0,
        "y18,47": 1.0,
        "y18,48": 1.0,
        "y18,49": 1.0,
        "y19,20": 1.0,
        "y19,21": 1.0,
        "y19,22": 1.0,
        "y19,23": 1.0,
        "y19,24": 1.0,
        "y19,25": 1.0,
        "y19,26": 1.0,
        "y19,27": 0.0,
        "y19,28": 1.0,
        "y19,29": 0.0,
        "y19,30": 1.0,
        "y19,31": 1.0,
        "y19,32": 1.0,
        "y19,33": 0.0,
        "y19,34": 1.0,
        "y19,35": 1.0,
        "y19,36": 1.0,
        "y19,37": 0.0,
        "y19,38": 1.0,
        "y19,40": 1.0,
        "y19,42": 1.0,
        "y19,43": 0.0,
        "y19,44": 1.0,
        "y19,45": 1.0,
        "y19,46": 1.0,
        "y19,47": 1.0,
        "y19,48": 1.0,
        "y20,21": 1.0,
        "y20,22": 1.0,
        "y20,23": 1.0,
        "y20,24": 1.0,
        "y20,25": 1.0,
        "y20,26": 1.0,
        "y20,27": 1.0,
        "y20,28": 1.0,
        "y20,30": 1.0,
        "y20,31": 1.0,
        "y20,32": 1.0,
        "y20,33": 1.0,
        "y20,34": 1.0,
        "y20,35": 1.0,
        "y20,36": 1.0,
        "y20,37": 1.0,
        "y20,38": 1.0,
        "y20,39": 1.0,
        "y20,40": 1.0,
        "y20,41": 1.0,
        "y20,42": 1.0,
        "y20,43": 0.0,
        "y20,44": 0.0,
        "y20,47": 1.0,
        "y20,48": 1.0,
        "y20,49": 1.0,
        "y21,23": 1.0,
        "y21,24": 0.0,
        "y21,25": 0.0,
        "y21,26": 0.0,
        "y21,27": 0.0,
        "y21,28": 1.0,
        "y21,29": 1.0,
        "y21,31": 0.0,
        "y21,32": 1.0,
        "y21,33": 0.0,
        "y21,34": 1.0,
        "y21,35": 1.0,
        "y21,36": 0.0,
        "y21,37": 1.0,
        "y21,38": 1.0,
        "y21,39": 1.0,
        "y21,40": 1.0,
        "y21,41": 1.0,
        "y21,42": 1.0,
        "y21,43": 1.0,
        "y21,45": 1.0,
        "y21,46": 1.0,
        "y21,47": 1.0,
        "y21,49": 1.0,
        "y22,23": 1.0,
        "y22,24": 1.0,
        "y22,25": 1.0,
        "y22,26": 1.0,
        "y22,27": 1.0,
        "y22,28": 1.0,
        "y22,29": 1.0,
        "y22,30": 1.0,
        "y22,31": 0.0,
        "y22,32": 1.0,
        "y22,33": 0.0,
        "y22,34": 0.0,
        "y22,35": 0.0,
        "y22,36": 1.0,
        "y22,37": 1.0,
        "y22,38": 0.0,
        "y22,39": 1.0,
        "y22,40": 0.0,
        "y22,41": 1.0,
        "y22,43": 0.0,
        "y22,44": 1.0,
        "y22,45": 1.0,
        "y22,46": 0.0,
        "y22,47": 1.0,
        "y22,49": 0.0,
        "y23,24": 1.0,
        "y23,25": 1.0,
        "y23,26": 0.0,
        "y23,27": 1.0,
        "y23,28": 1.0,
        "y23,29": 1.0,
        "y23,30": 0.0,
        "y23,31": 1.0,
        "y23,32": 1.0,
        "y23,33": 1.0,
        "y23,34": 1.0,
        "y23,35": 1.0,
        "y23,37": 1.0,
        "y23,38": 1.0,
        "y23,39": 1.0,
        "y23,40": 1.0,
        "y23,41": 1.0,
        "y23,42": 1.0,
        "y23,43": 1.0,
        "y23,44": 1.0,
        "y23,45": 1.0,
        "y23,46": 1.0,
        "y23,47": 1.0,
        "y23,48": 1.0,
        "y23,49": 1.0,
        "y24,25": 1.0,
        "y24,26": 1.0,
        "y24,27": 1.0,
        "y24,28": 1.0,
        "y24,29": 1.0,
        "y24,30": 1.0,
        "y24,31": 1.0,
        "y24,32": 1.0,
        "y24,33": 0.0,
        "y24,34": 1.0,
        "y24,35": 1.0,
        "y24,36": 1.0,
        "y24,37": 1.0,
        "y24,38": 1.0,
        "y24,39": 1.0,
        "y24,40": 1.0,
        "y24,41": 1.0,
        "y24,42": 1.0,
        "y24,43": 1.0,
        "y24,44": 1.0,
        "y24,45": 1.0,
        "y24,46": 1.0,
        "y24,47": 1.0,
        "y24,48": 1.0,
        "y24,49": 1.0,
        "y25,26": 0.0,
        "y25,27": 1.0,
        "y25,28": 1.0,
        "y25,29": 1.0,
        "y25,32": 1.0,
        "y25,34": 1.0,
        "y25,35": 1.0,
        "y25,36": 1.0,
        "y25,37": 1.0,
        "y25,38": 1.0,
        "y25,39": 1.0,
        "y25,40": 1.0,
        "y25,41": 0.0,
        "y25,42": 0.0,
        "y25,43": 1.0,
        "y25,44": 1.0,
        "y25,45": 1.0,
        "y25,46": 1.0,
        "y25,47": 0.0,
        "y25,48": 1.0,
        "y25,49": 1.0,
        "y26,27": 1.0,
        "y26,28": 0.0,
        "y26,29": 1.0,
        "y26,30": 1.0,
        "y26,31": 1.0,
        "y26,32": 1.0,
        "y26,33": 1.0,
        "y26,34": 1.0,
        "y26,37": 0.0,
        "y26,38": 1.0,
        "y26,39": 0.0,
        "y26,40": 1.0,
        "y26,41": 1.0,
        "y26,43": 1.0,
        "y26,44": 1.0,
        "y26,46": 0.0,
        "y26,47": 1.0,
        "y26,48": 1.0,
        "y26,49": 0.0,
        "y27,28": 1.0,
        "y27,29": 0.0,
        "y27,30": 1.0,
        "y27,31": 1.0,
        "y27,32": 0.0,
        "y27,33": 1.0,
        "y27,34": 1.0,
        "y27,35": 1.0,
        "y27,36": 0.0,
        "y27,37": 0.0,
        "y27,38": 1.0,
        "y27,39": 1.0,
        "y27,40": 1.0,
        "y27,42": 1.0,
        "y27,43": 0.0,
        "y27,44": 0.0,
        "y27,45": 1.0,
        "y27,47": 1.0,
        "y27,48": 1.0,
        "y27,49": 1.0,
        "y28,29": 0.0,
        "y28,30": 1.0,
        "y28,31": 1.0,
        "y28,32": 0.0,
        "y28,33": 1.0,
        "y28,34": 1.0,
        "y28,35": 0.0,
        "y28,36": 1.0,
        "y28,37": 0.0,
        "y28,38": 1.0,
        "y28,39": 1.0,
        "y28,40": 1.0,
        "y28,41": 0.0,
        "y28,42": 1.0,
        "y28,43": 1.0,
        "y28,44": 1.0,
        "y28,45": 1.0,
        "y28,46": 1.0,
        "y28,47": 1.0,
        "y28,48": 1.0,
        "y28,49": 1.0,
        "y29,30": 1.0,
        "y29,31": 1.0,
        "y29,32": 1.0,
        "y29,33": 1.0,
        "y29,34": 1.0,
        "y29,36": 1.0,
        "y29,37": 0.0,
        "y29,38": 1.0,
        "y29,39": 1.0,
        "y29,40": 1.0,
        "y29,42": 1.0,
        "y29,43": 1.0,
        "y29,44": 1.0,
        "y29,45": 1.0,
        "y29,46": 1.0,
        "y29,48": 0.0,
        "y29,49": 1.0,
        "y30,32": 1.0,
        "y30,33": 1.0,
        "y30,34": 0.0,
        "y30,35": 0.0,
        "y30,36": 1.0,
        "y30,37": 1.0,
        "y30,38": 1.0,
        "y30,40": 1.0,
        "y30,41": 1.0,
        "y30,42": 1.0,
        "y30,43": 1.0,
        "y30,44": 1.0,
        "y30,46": 1.0,
        "y30,47": 1.0,
        "y30,48": 1.0,
        "y30,49": 0.0,
        "y31,32": 1.0,
        "y31,33": 1.0,
        "y31,34": 0.0,
        "y31,35": 1.0,
        "y31,36": 1.0,
        "y31,37": 1.0,
        "y31,38": 1.0,
        "y31,39": 0.0,
        "y31,40": 1.0,
        "y31,41": 1.0,
        "y31,42": 1.0,
        "y31,43": 0.0,
        "y31,44": 0.0,
        "y31,45": 1.0,
        "y31,46": 1.0,
        "y31,47": 1.0,
        "y31,48": 0.0,
        "y31,49": 1.0,
        "y32,34": 1.0,
        "y32,35": 1.0,
        "y32,36": 1.0,
        "y32,37": 1.0,
        "y32,38": 1.0,
        "y32,39": 0.0,
        "y32,40": 1.0,
        "y32,41": 1.0,
        "y32,42": 1.0,
        "y32,43": 1.0,
        "y32,44": 1.0,
        "y32,45": 0.0,
        "y32,46": 1.0,
        "y32,47": 1.0,
        "y32,48": 0.0,
        "y32,49": 1.0,
        "y33,34": 1.0,
        "y33,35": 1.0,
        "y33,36": 1.0,
        "y33,37": 1.0,
        "y33,38": 1.0,
        "y33,39": 1.0,
        "y33,40": 1.0,
        "y33,43": 1.0,
        "y33,44": 0.0,
        "y33,45": 0.0,
        "y33,46": 0.0,
        "y33,48": 0.0,
        "y33,49": 1.0,
        "y34,35": 1.0,
        "y34,36": 1.0,
        "y34,37": 1.0,
        "y34,38": 1.0,
        "y34,39": 1.0,
        "y34,40": 0.0,
        "y34,41": 1.0,
        "y34,42": 1.0,
        "y34,43": 0.0,
        "y34,44": 1.0,
        "y34,45": 0.0,
        "y34,46": 1.0,
        "y34,47": 1.0,
        "y34,48": 1.0,
        "y34,49": 1.0,
        "y35,36": 1.0,
        "y35,38": 1.0,
        "y35,41": 1.0,
        "y35,42": 1.0,
        "y35,43": 1.0,
        "y35,44": 0.0,
        "y35,45": 1.0,
        "y35,46": 1.0,
        "y35,47": 0.0,
        "y35,48": 1.0,
        "y35,49": 1.0,
        "y36,37": 1.0,
        "y36,38": 1.0,
        "y36,39": 0.0,
        "y36,40": 1.0,
        "y36,41": 1.0,
        "y36,43": 1.0,
        "y36,44": 1.0,
        "y36,45": 1.0,
        "y36,46": 0.0,
        "y36,47": 1.0,
        "y36,48": 0.0,
        "y36,49": 0.0,
        "y37,38": 1.0,
        "y37,39": 1.0,
        "y37,40": 1.0,
        "y37,41": 0.0,
        "y37,42": 0.0,
        "y37,43": 1.0,
        "y37,44": 0.0,
        "y37,45": 0.0,
        "y37,47": 1.0,
        "y37,48": 1.0,
        "y37,49": 1.0,
        "y38,39": 1.0,
        "y38,41": 0.0,
        "y38,42": 1.0,
        "y38,43": 1.0,
        "y38,44": 1.0,
        "y38,45": 1.0,
        "y38,46": 1.0,
        "y38,47": 1.0,
        "y38,48": 1.0,
        "y39,40": 1.0,
        "y39,41": 0.0,
        "y39,42": 1.0,
        "y39,43": 1.0,
        "y39,44": 0.0,
        "y39,45": 0.0,
        "y39,46": 1.0,
        "y39,47": 1.0,
        "y39,48": 1.0,
        "y39,49": 1.0,
        "y40,41": 1.0,
        "y40,42": 1.0,
        "y40,43": 0.0,
        "y40,44": 1.0,
        "y40,45": 0.0,
        "y40,46": 1.0,
        "y40,47": 1.0,
        "y40,48": 1.0,
        "y41,42": 1.0,
        "y41,43": 1.0,
        "y41,44": 1.0,
        "y41,45": 0.0,
        "y41,46": 1.0,
        "y41,48": 1.0,
        "y41,49": 1.0,
        "y42,43": 1.0,
        "y42,44": 1.0,
        "y42,45": 0.0,
        "y42,46": 1.0,
        "y42,47": 1.0,
        "y42,48": 1.0,
        "y42,49": 1.0,
        "y43,44": 1.0,
        "y43,45": 1.0,
        "y43,47": 1.0,
        "y43,48": 0.0,
        "y43,49": 0.0,
        "y44,45": 1.0,
        "y44,46": 0.0,
        "y44,47": 1.0,
        "y44,48": 1.0,
        "y44,49": 1.0,
        "y45,46": 0.0,
        "y45,47": 1.0,
        "y45,48": 1.0,
        "y45,49": 1.0,
        "y46,47": 0.0,
        "y46,48": 1.0,
        "y46,49": 1.0,
        "y47,48": 0.0,
        "y48,49": 1.0,
        "x0": -0.0,
        "x1": -0.0,
        "x2": 1.0,
        "x3": -0.0,
        "x4": -0.0,
        "x5": 0.0,
        "x6": -0.0,
        "x7": -0.0,
        "x8": 1.0,
        "x9": 1.0,
        "x10": -0.0,
        "x11": -0.0,
        "x12": -0.0,
        "x13": -0.0,
        "x14": -0.0,
        "x15": -0.0,
        "x16": -0.0,
        "x17": -0.0,
        "x18": -0.0,
        "x19": -0.0,
        "x20": -0.0,
        "x21": -0.0,
        "x22": -0.0,
        "x23": 1.0,
        "x24": 1.0,
        "x25": 1.0,
        "x26": -0.0,
        "x27": 1.0,
        "x28": -0.0,
        "x29": -0.0,
        "x30": -0.0,
        "x31": -0.0,
        "x32": -0.0,
        "x33": -0.0,
        "x34": -0.0,
        "x35": 1.0,
        "x36": -0.0,
        "x37": -0.0,
        "x38": -0.0,
        "x39": -0.0,
        "x40": -0.0,
        "x41": -0.0,
        "x42": -0.0,
        "x43": -0.0,
        "x44": -0.0,
        "x45": 1.0,
        "x46": -0.0,
        "x47": -0.0,
        "x48": 1.0,
        "x49": 1.0
    }
}