{
    "name": "OR10x100-0.25_5.dat-0",
    "bilevel_type": "optimistic",
    "status": "open with feasible point",
    "difficulty": "hard",
    "objective_value": 21437.0,
    "upper_level_decisions": {
        "x2": 1.0,
        "x4": 1.0,
        "x7": 1.0,
        "x8": 1.0,
        "x9": 1.0,
        "x17": 1.0,
        "x21": 1.0,
        "x27": 1.0,
        "x29": 1.0,
        "x31": 1.0,
        "x36": 1.0,
        "x40": 1.0,
        "x51": 1.0,
        "x52": 1.0,
        "x55": 1.0,
        "x64": 1.0,
        "x66": 1.0,
        "x70": 1.0,
        "x75": 1.0,
        "x77": 1.0,
        "x80": 1.0,
        "x89": 1.0,
        "x91": 1.0,
        "x92": 1.0,
        "x93": 1.0,
        "x96": 1.0
    },
    "lower_level_decisions": {
        "y0": 1.0,
        "y3": 1.0,
        "y6": 1.0,
        "y10": 1.0,
        "y12": 1.0,
        "y14": 1.0,
        "y15": 1.0,
        "y22": 1.0,
        "y23": 1.0,
        "y25": 1.0,
        "y28": 1.0,
        "y37": 1.0,
        "y39": 1.0,
        "y43": 1.0,
        "y45": 1.0,
        "y46": 1.0,
        "y48": 1.0,
        "y50": 1.0,
        "y57": 1.0,
        "y59": 1.0,
        "y67": 1.0,
        "y84": 1.0,
        "y85": 1.0,
        "y98": 1.0
    }
}